burp_ui_monitor-1.1.1.data/data/share/burpui/etc/buimonitor.sample.cfg
burpui_monitor/RELEASE
burpui_monitor/VERSION
burpui_monitor/__init__.py
burpui_monitor/__main__.py
burpui_monitor/_compat.py
burpui_monitor/_json.py
burpui_monitor/config.py
burpui_monitor/datastructures.py
burpui_monitor/decorators.py
burpui_monitor/desc.py
burpui_monitor/exceptions.py
burpui_monitor/security.py
burpui_monitor/utils.py
burpui_monitor/__pycache__/__init__.cpython-39.pyc
burpui_monitor/__pycache__/desc.cpython-39.pyc
burpui_monitor/engines/__init__.py
burpui_monitor/engines/monitor.py
burpui_monitor/misc/__init__.py
burpui_monitor/misc/backend/__init__.py
burpui_monitor/misc/backend/burp1.py
burpui_monitor/misc/backend/burp2.py
burpui_monitor/misc/backend/interface.py
burpui_monitor/misc/backend/multi.py
burpui_monitor/misc/backend/parallel.py
burpui_monitor/misc/backend/.ropeproject/config.py
burpui_monitor/misc/backend/.ropeproject/globalnames
burpui_monitor/misc/backend/.ropeproject/history
burpui_monitor/misc/backend/.ropeproject/objectdb
burpui_monitor/misc/backend/utils/__init__.py
burpui_monitor/misc/backend/utils/burp2.py
burpui_monitor/misc/backend/utils/constant.py
burpui_monitor/misc/parser/__init__.py
burpui_monitor/misc/parser/burp1.py
burpui_monitor/misc/parser/burp2.py
burpui_monitor/misc/parser/doc.py
burpui_monitor/misc/parser/interface.py
burpui_monitor/misc/parser/openssl.py
burpui_monitor/misc/parser/utils.py
burpui_monitor/misc/parser/.ropeproject/config.py
burpui_monitor/misc/parser/.ropeproject/globalnames
burpui_monitor/misc/parser/.ropeproject/history
burpui_monitor/misc/parser/.ropeproject/objectdb
burpui_monitor/tools/__init__.py
burpui_monitor/tools/logging.py
burp_ui_monitor-1.1.1.dist-info/METADATA
burp_ui_monitor-1.1.1.dist-info/WHEEL
burp_ui_monitor-1.1.1.dist-info/entry_points.txt
burp_ui_monitor-1.1.1.dist-info/top_level.txt
burp_ui_monitor-1.1.1.dist-info/RECORD
