Metadata-Version: 2.1
Name: burp-ui-monitor
Version: 1.1.1
Summary: Burp-UI is a web-ui for burp backup written in python with Flask and jQuery/Bootstrap
Home-page: https://git.ziirish.me/ziirish/burp-ui
Author: Benjamin SANS (Ziirish)
Author-email: hi+burpui@ziirish.me
License: BSD 3-clause
Keywords: burp web ui backup monitoring
Platform: UNKNOWN
Classifier: Intended Audience :: System Administrators
Classifier: Natural Language :: English
Classifier: License :: OSI Approved :: BSD License
Classifier: Operating System :: POSIX :: Linux
Classifier: Programming Language :: Python
Classifier: Programming Language :: Python :: 3.6
Classifier: Topic :: System :: Archiving :: Backup
Classifier: Topic :: System :: Monitoring
Requires-Dist: trio (==0.22.0)
Requires-Dist: arrow (==1.2.3)
Requires-Dist: tzlocal (==4.3)
Requires-Dist: pyOpenSSL (==23.0.0)
Requires-Dist: configobj (==5.0.8)
